LICENSE.txt
MANIFEST.in
setup.py
TASSELpy/TASSELbridge.py
TASSELpy/__init__.py
TASSELpy/javaObj.py
TASSELpy/data/__init__.py
TASSELpy/data/data_constants.py
TASSELpy/data/mdp_genotype.hmp.txt
TASSELpy/data/mdp_genotype.short.hmp.txt
TASSELpy/data/mdp_population_structure.txt
TASSELpy/data/mdp_traits.txt
TASSELpy/java/__init__.py
TASSELpy/java/lang/Boolean.py
TASSELpy/java/lang/Byte.py
TASSELpy/java/lang/Class.py
TASSELpy/java/lang/Comparable.py
TASSELpy/java/lang/Double.py
TASSELpy/java/lang/Enum.py
TASSELpy/java/lang/Float.py
TASSELpy/java/lang/Integer.py
TASSELpy/java/lang/Iterable.py
TASSELpy/java/lang/Long.py
TASSELpy/java/lang/Number.py
TASSELpy/java/lang/Object.py
TASSELpy/java/lang/Runnable.py
TASSELpy/java/lang/String.py
TASSELpy/java/lang/Thread.py
TASSELpy/java/lang/__init__.py
TASSELpy/java/lang/reflect/Array.py
TASSELpy/java/lang/reflect/__init__.py
TASSELpy/java/util/AbstractMap.py
TASSELpy/java/util/AbstractSequentialList.py
TASSELpy/java/util/ArrayList.py
TASSELpy/java/util/Collection.py
TASSELpy/java/util/Deque.py
TASSELpy/java/util/FilterList.py
TASSELpy/java/util/HashMap.py
TASSELpy/java/util/Iterator.py
TASSELpy/java/util/LinkedList.py
TASSELpy/java/util/List.py
TASSELpy/java/util/ListIterator.py
TASSELpy/java/util/Map.py
TASSELpy/java/util/Queue.py
TASSELpy/java/util/Set.py
TASSELpy/java/util/__init__.py
TASSELpy/lib/LiuExt.jar
TASSELpy/lib/batik-awt-util.jar
TASSELpy/lib/batik-css.jar
TASSELpy/lib/batik-dom.jar
TASSELpy/lib/batik-ext.jar
TASSELpy/lib/batik-gui-util.jar
TASSELpy/lib/batik-gvt.jar
TASSELpy/lib/batik-parser.jar
TASSELpy/lib/batik-svg-dom.jar
TASSELpy/lib/batik-svggen.jar
TASSELpy/lib/batik-util.jar
TASSELpy/lib/batik-xml.jar
TASSELpy/lib/biojava3-alignment-3.0.jar
TASSELpy/lib/biojava3-core-3.0.jar
TASSELpy/lib/biojava3-phylo-3.0.jar
TASSELpy/lib/cisd-jhdf5-batteries_included_lin_win_mac.jar
TASSELpy/lib/colt.jar
TASSELpy/lib/commons-math-2.2.jar
TASSELpy/lib/ejml-0.23.jar
TASSELpy/lib/forester.jar
tasselpy.egg-info/PKG-INFO
tasselpy.egg-info/SOURCES.txt
tasselpy.egg-info/dependency_links.txt
tasselpy.egg-info/top_level.txt