Metadata-Version: 1.1
Name: tasselpy
Version: 0.22
Summary: A Python API for TASSEL
Home-page: https://github.com/er432/TASSELpy
Author: Eli Rodgers-Melnick
Author-email: er432@cornell.edu
License: BSD
Keywords: Genomics,Quantitative genetics,java
Platform: Linux
Platform: Mac OSX
Platform: Windows
Platform: Unix
Classifier: Development Status :: 3 - Alpha
Classifier: Intended Audience :: Developers
Classifier: Intended Audience :: Science/Research
Classifier: License :: OSI Approved :: BSD License
Classifier: Operating System :: OS Independent
Classifier: Programming Language :: Python :: 2
Classifier: Programming Language :: Python :: 2.7
Classifier: Topic :: Software Development :: Libraries :: Python Modules
Classifier: Topic :: Scientific/Engineering :: Bio-Informatics
Classifier: Topic :: Scientific/Engineering :: Information Analysis
